ipfabric_diagrams/__init__.py
ipfabric_diagrams/graphs.py
ipfabric_diagrams/icmp.py
ipfabric_diagrams-6.5.0.dist-info/LICENSE
ipfabric_diagrams-6.5.0.dist-info/METADATA
ipfabric_diagrams-6.5.0.dist-info/WHEEL
ipfabric_diagrams-6.5.0.dist-info/RECORD
