Metadata-Version: 2.1
Name: ipfabric-diagrams
Version: 6.5.0
Summary: DEPRECATED: Python package for interacting with IP Fabric Diagrams
Home-page: https://gitlab.com/ip-fabric/integrations/python-ipfabric-diagrams
License: MIT
Keywords: ipfabric,ip-fabric,community-fabric
Author: Justin Jeffery
Author-email: justin.jeffery@ipfabric.io
Requires-Python: >=3.8.1,<4.0.0
Classifier: License :: OSI Approved :: MIT License
Classifier: Programming Language :: Python :: 3
Classifier: Programming Language :: Python :: 3.9
Classifier: Programming Language :: Python :: 3.10
Classifier: Programming Language :: Python :: 3.11
Classifier: Programming Language :: Python :: 3.12
Requires-Dist: ipfabric (==6.5.0)
Project-URL: Changelog, https://gitlab.com/ip-fabric/integrations/python-ipfabric-diagrams/-/blob/develop/CHANGELOG.md
Project-URL: IP Fabric, https://ipfabric.io/
Project-URL: Repository, https://gitlab.com/ip-fabric/integrations/python-ipfabric-diagrams
